exemple_package/__init__.py
exemple_package/csvfile.py
exemple_package/file.py
exemple_package/jofile.py
BENALLAL_IMANE-0.0.1.dist-info/LICENSE
BENALLAL_IMANE-0.0.1.dist-info/METADATA
BENALLAL_IMANE-0.0.1.dist-info/WHEEL
BENALLAL_IMANE-0.0.1.dist-info/top_level.txt
BENALLAL_IMANE-0.0.1.dist-info/RECORD
