Metadata-Version: 2.1
Name: BENALLAL-IMANE
Version: 0.0.1
Summary: json+csv+text
Home-page: https://github.com/pypa/sampleproject
Author: IMANE BEN
Author-email: IMANE@BENALLAL.com
Project-URL: Bug Tracker, https://github.com/pypa/sampleproject/issues
Classifier: Programming Language :: Python :: 3
Classifier: License :: OSI Approved :: MIT License
Classifier: Operating System :: OS Independent
Requires-Python: >=3.10
License-File: LICENSE
